TSP_Reader.py
helper_monkey.py
markowitzify.py
markowitzify-0.0.5.dist-info/LICENSE.txt
markowitzify-0.0.5.dist-info/METADATA
markowitzify-0.0.5.dist-info/WHEEL
markowitzify-0.0.5.dist-info/top_level.txt
markowitzify-0.0.5.dist-info/RECORD
