Metadata-Version: 2.1
Name: markowitzify
Version: 0.0.5
Summary: Markowitzify will implement a variety of portfolio and stock/cryptocurrency analysis methods to optimize portfolios or trading strategies.  The two primary classes are portfolio and stonks.
Home-page: https://github.com/metalcorebear/Markowitzify
Author: metalcorebear
Author-email: mark.mbailey@gmail.com
License: UNKNOWN
Platform: UNKNOWN
Classifier: Programming Language :: Python :: 3.7
Classifier: License :: OSI Approved :: MIT License
Classifier: Operating System :: OS Independent
Requires-Python: >=3.7
Requires-Dist: requests
Requires-Dist: pandas
Requires-Dist: numpy
Requires-Dist: sklearn
Requires-Dist: pandas-datareader
Requires-Dist: scipy
Requires-Dist: statsmodels
